pythomac/__init__.py
pythomac/flux_analyst.py
pythomac/parser_output.py
pythomac/utils/__init__.py
pythomac/utils/exceptions.py
pythomac/utils/files.py
pythomac/utils/plots.py
pythomac-1.0.2.dist-info/METADATA
pythomac-1.0.2.dist-info/WHEEL
pythomac-1.0.2.dist-info/licenses/LICENSE
pythomac-1.0.2.dist-info/RECORD
